gdeep/__init__.py
gdeep/_version.py
gdeep/analysis/__init__.py
gdeep/analysis/decision_boundary/__init__.py
gdeep/analysis/decision_boundary/compute_topology.py
gdeep/analysis/decision_boundary/decision_boundary_calculator.py
gdeep/analysis/decision_boundary/utility.py
gdeep/analysis/decision_boundary/tests/__init__.py
gdeep/analysis/decision_boundary/tests/test_compute_topology.py
gdeep/analysis/decision_boundary/tests/test_decision_boundary_calculator.py
gdeep/analysis/interpretability/__init__.py
gdeep/analysis/interpretability/attribution_factory.py
gdeep/analysis/interpretability/captum.py
gdeep/data/__init__.py
gdeep/data/_utils.py
gdeep/data/abstract_preprocessing.py
gdeep/data/dataset_factory.py
gdeep/data/preprocessing_pipeline.py
gdeep/data/transforming_dataset.py
gdeep/data/datasets/__init__.py
gdeep/data/datasets/_data_cloud.py
gdeep/data/datasets/base_dataloaders.py
gdeep/data/datasets/build_datasets.py
gdeep/data/datasets/categorical_data.py
gdeep/data/datasets/dataloader_cloud.py
gdeep/data/datasets/dataset_cloud.py
gdeep/data/datasets/dataset_for_image.py
gdeep/data/datasets/dataset_form_array.py
gdeep/data/datasets/graph_datasets.py
gdeep/data/datasets/orbit.py
gdeep/data/datasets/parallel_orbit.py
gdeep/data/datasets/persistence_diagrams_from_files.py
gdeep/data/datasets/persistence_diagrams_from_graphs_builder.py
gdeep/data/datasets/tori.py
gdeep/data/datasets/tests/__init__.py
gdeep/data/datasets/tests/test_data_cloud.py
gdeep/data/datasets/tests/test_dataset_cloud.py
gdeep/data/datasets/tests/test_dataset_for_image.py
gdeep/data/datasets/tests/test_dataset_from_array.py
gdeep/data/datasets/tests/test_parallel_orbit.py
gdeep/data/datasets/tests/test_persistence_diagrams_from_graphs_builder.py
gdeep/data/persistence_diagrams/__init__.py
gdeep/data/persistence_diagrams/one_hot_persistence_diagram.py
gdeep/data/persistence_diagrams/tests/__init__.py
gdeep/data/persistence_diagrams/tests/test_one_hot_persistence_diagram.py
giotto_deep-0.0.4.dist-info/LICENSE
giotto_deep-0.0.4.dist-info/METADATA
giotto_deep-0.0.4.dist-info/WHEEL
giotto_deep-0.0.4.dist-info/dependency_links.txt
giotto_deep-0.0.4.dist-info/top_level.txt
giotto_deep-0.0.4.dist-info/RECORD
