Metadata-Version: 2.1
Name: giotto-deep
Version: 0.0.4
Summary: Toolbox for Deep Learning and Topological Data Analysis.
Home-page: https://github.com/giotto-ai/giotto-deep
Download-URL: https://github.com/giotto-ai/giotto-deep/tarball/v0.0.4
Maintainer: Matteo Caorsi
Maintainer-email: maintainers@giotto.ai
License: GNU AGPLv3
Keywords: deep learning,topological data analysis,persistent homology,persistence diagrams
Classifier: Intended Audience :: Science/Research
Classifier: Intended Audience :: Developers
Classifier: License :: OSI Approved
Classifier: Programming Language :: Python
Classifier: Topic :: Software Development
Classifier: Topic :: Scientific/Engineering
Classifier: Operating System :: Microsoft :: Windows
Classifier: Operating System :: POSIX
Classifier: Operating System :: Unix
Classifier: Operating System :: MacOS
Classifier: Programming Language :: Python :: 3.7
Classifier: Programming Language :: Python :: 3.8
Classifier: Programming Language :: Python :: 3.9
License-File: LICENSE
Requires-Dist: giotto-tda >=0.6.0
Requires-Dist: numpy <=1.23.3
Requires-Dist: pandas
Requires-Dist: plotly
Requires-Dist: matplotlib <=3.6.3
Requires-Dist: matplotlib-venn
Requires-Dist: scikit-learn ==1.1.1
Requires-Dist: torch ==1.12.1
Requires-Dist: spacy
Requires-Dist: scipy
Requires-Dist: networkx
Requires-Dist: torch-tb-profiler
Requires-Dist: torchdiffeq
Requires-Dist: torchensemble
Requires-Dist: torchtext
Requires-Dist: torchvision
Requires-Dist: torchdata
Requires-Dist: transformers
Requires-Dist: einops
Requires-Dist: tensorboard
Requires-Dist: captum
Requires-Dist: rq
Requires-Dist: rq-dashboard
Requires-Dist: redis
Requires-Dist: psutil
Requires-Dist: kaleido
Requires-Dist: html2image
Requires-Dist: optuna
Requires-Dist: sphinx-rtd-theme
Requires-Dist: giotto-ph
Requires-Dist: tqdm
Requires-Dist: Pillow <=9.5.0
Requires-Dist: h5py
Requires-Dist: mysql-connector-python
Requires-Dist: dotmap
Requires-Dist: sympy
Requires-Dist: google-cloud-storage
Requires-Dist: wget
Requires-Dist: ipython
Requires-Dist: jsonpickle
Requires-Dist: gudhi
Requires-Dist: pre-commit
Requires-Dist: typing-extensions ; python_version == "3.7"
Provides-Extra: doc
Requires-Dist: openml ; extra == 'doc'
Requires-Dist: sphinx ; extra == 'doc'
Requires-Dist: nbconvert ; extra == 'doc'
Requires-Dist: sphinx-issues ; extra == 'doc'
Requires-Dist: sphinx-rtd-theme ; extra == 'doc'
Requires-Dist: numpydoc ; extra == 'doc'
Provides-Extra: examples
Requires-Dist: jupyter ; extra == 'examples'
Requires-Dist: pandas ; extra == 'examples'
Requires-Dist: openml ; extra == 'examples'
Requires-Dist: plotly ; extra == 'examples'
Provides-Extra: tests
Requires-Dist: pytest ; extra == 'tests'
Requires-Dist: flake8 ; extra == 'tests'
Requires-Dist: mypy ; extra == 'tests'
